reag/__init__.py
reag/client.py
reag/prompt.py
reag/schema.py
reag-0.0.6.dist-info/METADATA
reag-0.0.6.dist-info/WHEEL
reag-0.0.6.dist-info/RECORD
